shamiko/__init__.py
shamiko/app.py
shamiko/cli.py
shamiko/gdb_rpc.py
shamiko/proc_utils.py
shamiko/py.typed
shamiko/session.py
shamiko/session_utils.py
shamiko/gdb/__init__.py
shamiko/gdb/server.py
shamiko/gdb/wrapper.py
shamiko/simple_rpc/__init__.py
shamiko/simple_rpc/client.py
shamiko/simple_rpc/reader.py
shamiko/simple_rpc/serializer.py
shamiko/simple_rpc/server.py
shamiko/templates/attach_pdb.py.template
shamiko/templates/bootstrap.py.template
shamiko-0.1.0.dist-info/LICENSE
shamiko-0.1.0.dist-info/METADATA
shamiko-0.1.0.dist-info/WHEEL
shamiko-0.1.0.dist-info/entry_points.txt
shamiko-0.1.0.dist-info/top_level.txt
shamiko-0.1.0.dist-info/RECORD
