Metadata-Version: 2.1
Name: shamiko
Version: 0.1.0
Summary: Shamiko ga waruindayo
Home-page: https://github.com/bonprosoft/shamiko
Author: Yuki Igarashi
Author-email: me@bonprosoft.com
License: MIT License
Platform: UNKNOWN
Classifier: Programming Language :: Python :: 2
Classifier: Programming Language :: Python :: 2.7
Classifier: Programming Language :: Python :: 3.5
Classifier: Programming Language :: Python :: 3.6
Classifier: Programming Language :: Python :: 3.7
Classifier: Programming Language :: Python :: 3.8
Classifier: Programming Language :: Python :: 3.9
Classifier: Programming Language :: Python
Classifier: License :: OSI Approved :: MIT License
Requires-Dist: psutil (<6,>=5.6.7)
Requires-Dist: Jinja2 (<3,>=2.10.3)
